glnext_compiler.cp38-win_amd64.pyd
glnext_compiler-1.0.1.dist-info/LICENSE
glnext_compiler-1.0.1.dist-info/METADATA
glnext_compiler-1.0.1.dist-info/WHEEL
glnext_compiler-1.0.1.dist-info/top_level.txt
glnext_compiler-1.0.1.dist-info/RECORD
