Metadata-Version: 2.1
Name: glnext-compiler
Version: 1.0.1
Summary: UNKNOWN
Home-page: https://github.com/glnext/glnext-compiler/
Author: Szabolcs Dombi
Author-email: cprogrammer1994@gmail.com
License: MIT
Platform: UNKNOWN
